htmlcomparator/__init__.py
htmlcomparator/html_comparator.py
tests/__init__.py
tests/test_parse.py
htmlcomparator-0.1.0.dist-info/LICENSE
htmlcomparator-0.1.0.dist-info/METADATA
htmlcomparator-0.1.0.dist-info/WHEEL
htmlcomparator-0.1.0.dist-info/top_level.txt
htmlcomparator-0.1.0.dist-info/RECORD
