Metadata-Version: 2.1
Name: htmlcomparator
Version: 0.1.0
Summary: An html comparator that can output the differences between html code
Home-page: https://github.com/in-the-ocean/htmlcomparator
Author: Mengjia Zhao
Author-email: lucyzmj0914@gmail.com
License: UNKNOWN
Platform: UNKNOWN
Classifier: Programming Language :: Python :: 3
Classifier: License :: OSI Approved :: Apache Software License
Classifier: Operating System :: OS Independent
Requires-Python: >=3.6
